strumenti/__init__.py
strumenti/coordinate.py
strumenti/notify.py
strumenti/packages.py
strumenti/plot.py
strumenti/psql.py
strumenti/system.py
strumenti/tests/__init__.py
strumenti/tests/fixtures.py
strumenti/tests/test_coordinate.py
strumenti/tests/test_notify.py
strumenti/tests/test_plot.py
strumenti/tests/test_psql.py
strumenti/tests/test_system.py
strumenti-1.0.1.dist-info/DESCRIPTION.rst
strumenti-1.0.1.dist-info/METADATA
strumenti-1.0.1.dist-info/RECORD
strumenti-1.0.1.dist-info/WHEEL
strumenti-1.0.1.dist-info/metadata.json
strumenti-1.0.1.dist-info/top_level.txt
