Metadata-Version: 2.0
Name: strumenti
Version: 1.0.1
Summary: Common tools universally applicable to Python 3 packages.
Home-page: UNKNOWN
Author: Timothy Helton
Author-email: timothy.j.helton@gmail.com
License: BSD
Keywords: common tools utility
Platform: UNKNOWN
Classifier: Development Status :: 5 - Production/Stable
Classifier: Environment :: Console
Classifier: Intended Audience :: Developers
Classifier: License :: OSI Approved
Classifier: Natural Language :: English
Classifier: Operating System :: OS Independent
Classifier: Programming Language :: Python :: 3
Classifier: Topic :: Software Development :: Build Tools
Requires-Dist: Pint
Requires-Dist: chromalog
Requires-Dist: matplotlib
Requires-Dist: numpy
Requires-Dist: psycopg2
Requires-Dist: pytest
Requires-Dist: wrapt
